WaterNetworkAnalysis/WaterNetworkAnalysis.py
WaterNetworkAnalysis/__init__.py
WaterNetworkAnalysis-0.4.0.dist-info/LICENSE
WaterNetworkAnalysis-0.4.0.dist-info/METADATA
WaterNetworkAnalysis-0.4.0.dist-info/WHEEL
WaterNetworkAnalysis-0.4.0.dist-info/top_level.txt
WaterNetworkAnalysis-0.4.0.dist-info/RECORD
