Metadata-Version: 2.1
Name: WaterNetworkAnalysis
Version: 0.4.0
Summary: Set of tools for input preparation for conserved water search from MD trajectories (gromacs, amber) and their analysis
Author: Domagoj Fijan, Marko Jukic, Urban Bren
Author-email: Jelena Tosovic <jecat_90@live.com>
License: GNU GENERAL PUBLIC LICENSE
Project-URL: Homepage, https://github.com/JecaTosovic/WaterNetworkAnalysis
Project-URL: Documentation, https://WaterNetworkAnalysis.readthedocs.io/
Project-URL: Source, https://github.com/JecaTosovic/WaterNetworkAnalysis
Project-URL: Issue, https://github.com/JecaTosovic/WaterNetworkAnalysis/issues
Keywords: simulation,analysis,molecular dynamics,biosimulation,conserved water
Classifier: Development Status :: 4 - Beta
Classifier: Intended Audience :: Science/Research
Classifier: Topic :: Scientific/Engineering :: Chemistry
Classifier: Topic :: Scientific/Engineering :: Bio-Informatics
Classifier: Programming Language :: Python :: 3.9
Classifier: Programming Language :: Python :: 3.10
Classifier: Programming Language :: Python :: 3.11
Classifier: Programming Language :: Python :: 3.12
Requires-Python: >=3.9
License-File: LICENSE
Requires-Dist: ConservedWaterSearch >=0.1.0
Requires-Dist: MDAnalysis >=2.4.0
Requires-Dist: numpy >=1.22
Requires-Dist: scipy >=1.0.0
Requires-Dist: wget >=3.0.0
